ojax/__init__.py
ojax/otree.py
ojax/pureclass.py
ojax/py.typed
ojax-4.0.1.dist-info/LICENSE
ojax-4.0.1.dist-info/METADATA
ojax-4.0.1.dist-info/WHEEL
ojax-4.0.1.dist-info/top_level.txt
ojax-4.0.1.dist-info/RECORD
