Metadata-Version: 2.1
Name: ojax
Version: 4.0.1
Summary: An extension for modular JAX code.
Author: Yuesong Shen
License: Apache-2.0
Project-URL: Homepage, https://github.com/ysngshn/ojax
Requires-Python: >=3.10
License-File: LICENSE
Requires-Dist: typing-extensions
Requires-Dist: jax
Provides-Extra: dev
Requires-Dist: coverage; extra == "dev"
Requires-Dist: mypy; extra == "dev"
Requires-Dist: black; extra == "dev"
Requires-Dist: twine; extra == "dev"
Requires-Dist: sphinx; extra == "dev"
Requires-Dist: myst-parser; extra == "dev"
Requires-Dist: sphinx-book-theme; extra == "dev"
Requires-Dist: sphinx-rtd-theme; extra == "dev"
Requires-Dist: sphinx-readme; extra == "dev"
